client/__init__.py
client/api.py
client/client.py
client/command_line.py
itreat_lotr-0.0.3.dist-info/METADATA
itreat_lotr-0.0.3.dist-info/WHEEL
itreat_lotr-0.0.3.dist-info/entry_points.txt
itreat_lotr-0.0.3.dist-info/license.md
itreat_lotr-0.0.3.dist-info/top_level.txt
itreat_lotr-0.0.3.dist-info/RECORD
