Metadata-Version: 2.1
Name: itreat-lotr
Version: 0.0.3
Summary: SDK for Lord of the Rings API
Home-page: https://github.com/isaak-treat/LotRIsaakSDK
Author: Isaak Treat
Author-email: isaaktreaty@gmail.com
License: UNKNOWN
Platform: UNKNOWN
Requires-Python: >=3.6
License-File: license.md
